bioontologies/__init__.py
bioontologies/__main__.py
bioontologies/cli.py
bioontologies/constants.py
bioontologies/gilda_utils.py
bioontologies/ner.py
bioontologies/obograph.py
bioontologies/py.typed
bioontologies/robot.py
bioontologies/version.py
bioontologies/relations/__init__.py
bioontologies/relations/api.py
bioontologies/relations/data.json
bioontologies/relations/data_owl.json
bioontologies/relations/data_rdf.json
bioontologies/relations/data_rdfs.json
bioontologies/upgrade/__init__.py
bioontologies/upgrade/data.tsv
bioontologies/upgrade/import_debio.py
bioontologies-0.7.2.dist-info/licenses/LICENSE
bioontologies-0.7.2.dist-info/METADATA
bioontologies-0.7.2.dist-info/WHEEL
bioontologies-0.7.2.dist-info/entry_points.txt
bioontologies-0.7.2.dist-info/top_level.txt
bioontologies-0.7.2.dist-info/RECORD
