Metadata-Version: 2.4
Name: bioontologies
Version: 0.7.2
Summary: Tools for biomedical ontologies
Author-email: Charles Tapley Hoyt <cthoyt@gmail.com>
Maintainer-email: Charles Tapley Hoyt <cthoyt@gmail.com>
License: MIT License
Project-URL: Bug Tracker, https://github.com/biopragmatics/bioontologies/issues
Project-URL: Homepage, https://github.com/biopragmatics/bioontologies
Project-URL: Repository, https://github.com/biopragmatics/bioontologies.git
Project-URL: Documentation, https://bioontologies.readthedocs.io
Keywords: snekpack,cookiecutter,ontologies,OBO Foundry,knowledge graphs,biomedicine,biology,systems biology,networks biology
Classifier: Development Status :: 1 - Planning
Classifier: Environment :: Console
Classifier: Intended Audience :: Developers
Classifier: License :: OSI Approved :: MIT License
Classifier: Operating System :: OS Independent
Classifier: Framework :: Pytest
Classifier: Framework :: tox
Classifier: Framework :: Sphinx
Classifier: Programming Language :: Python
Classifier: Programming Language :: Python :: 3.10
Classifier: Programming Language :: Python :: 3.11
Classifier: Programming Language :: Python :: 3.12
Classifier: Programming Language :: Python :: 3 :: Only
Requires-Python: >=3.10
License-File: LICENSE
Requires-Dist: bioregistry>=0.12.5
Requires-Dist: curies>=0.6.0
Requires-Dist: requests
Requires-Dist: pydantic>=2.0
Requires-Dist: typing_extensions
Requires-Dist: pystow
Requires-Dist: pandas
Requires-Dist: ssslm
Provides-Extra: tests
Requires-Dist: pytest; extra == "tests"
Requires-Dist: coverage; extra == "tests"
Provides-Extra: docs
Requires-Dist: sphinx>=8; extra == "docs"
Requires-Dist: sphinx-rtd-theme>=3.0; extra == "docs"
Requires-Dist: sphinx-click; extra == "docs"
Requires-Dist: sphinx_automodapi; extra == "docs"
Dynamic: license-file
